{
    "team": "DMV Vandals",
    "source": "gamechanger",
    "players": [
        {
            "first": "Mike",
            "last": "Barkett",
            "number": 0,
            "stats": {
                "g": 2,
                "pa": 5,
                "ab": 5,
                "r": 1,
                "h": 1,
                "2b": 1,
                "3b": 0,
                "hr": 0,
                "rbi": 0,
                "sb": 0,
                "cs": 0,
                "bb": 0,
                "so": 2,
                "sol": 2,
                "ba": 0.2,
                "obp": 0.2,
                "slg": 0.4,
                "ops": 0.6,
                "tb": 2,
                "gdp": 0,
                "xbh": 1,
                "hbp": 0,
                "sac": 0,
                "roe": 0,
                "lob": 8,
                "barisp": 0,
                "babip": 0.333
            }
        },
        {
            "first": "Garrison",
            "last": "Burnett",
            "number": 0,
            "stats": {
                "g": 9,
                "pa": 33,
                "ab": 24,
                "r": 8,
                "h": 7,
                "2b": 0,
                "3b": 0,
                "hr": 0,
                "rbi": 1,
                "sb": 3,
                "cs": 2,
                "bb": 7,
                "so": 8,
                "sol": 5,
                "ba": 0.292,
                "obp": 0.485,
                "slg": 0.292,
                "ops": 0.777,
                "tb": 7,
                "gdp": 0,
                "xbh": 0,
                "hbp": 2,
                "sac": 0,
                "roe": 1,
                "lob": 13,
                "barisp": 0.25,
                "babip": 0.438
            }
        },
        {
            "first": "Tim",
            "last": "Denevi",
            "number": 0,
            "stats": {
                "g": 7,
                "pa": 28,
                "ab": 25,
                "r": 6,
                "h": 9,
                "2b": 3,
                "3b": 1,
                "hr": 0,
                "rbi": 6,
                "sb": 0,
                "cs": 0,
                "bb": 2,
                "so": 7,
                "sol": 0,
                "ba": 0.36,
                "obp": 0.407,
                "slg": 0.56,
                "ops": 0.967,
                "tb": 14,
                "gdp": 0,
                "xbh": 4,
                "hbp": 0,
                "sac": 0,
                "roe": 0,
                "lob": 16,
                "barisp": 0.273,
                "babip": 0.5
            }
        },
        {
            "first": "Jeff",
            "last": "Frey III",
            "number": 0,
            "stats": {
                "g": 7,
                "pa": 24,
                "ab": 19,
                "r": 5,
                "h": 5,
                "2b": 1,
                "3b": 0,
                "hr": 0,
                "rbi": 6,
                "sb": 2,
                "cs": 0,
                "bb": 3,
                "so": 4,
                "sol": 2,
                "ba": 0.263,
                "obp": 0.417,
                "slg": 0.316,
                "ops": 0.732,
                "tb": 6,
                "gdp": 0,
                "xbh": 1,
                "hbp": 2,
                "sac": 0,
                "roe": 0,
                "lob": 10,
                "barisp": 0.444,
                "babip": 0.333
            }
        },
        {
            "first": "Nathan",
            "last": "Hammond",
            "number": 0,
            "stats": {
                "g": 2,
                "pa": 5,
                "ab": 3,
                "r": 3,
                "h": 1,
                "2b": 0,
                "3b": 0,
                "hr": 0,
                "rbi": 0,
                "sb": 0,
                "cs": 0,
                "bb": 2,
                "so": 0,
                "sol": 0,
                "ba": 0.333,
                "obp": 0.6,
                "slg": 0.333,
                "ops": 0.933,
                "tb": 1,
                "gdp": 0,
                "xbh": 0,
                "hbp": 0,
                "sac": 0,
                "roe": 0,
                "lob": 2,
                "barisp": 0.5,
                "babip": 0.333
            }
        },
        {
            "first": "Tanner",
            "last": "Heltibridle",
            "number": 0,
            "stats": {
                "g": 8,
                "pa": 36,
                "ab": 24,
                "r": 8,
                "h": 10,
                "2b": 4,
                "3b": 0,
                "hr": 0,
                "rbi": 8,
                "sb": 1,
                "cs": 0,
                "bb": 9,
                "so": 4,
                "sol": 0,
                "ba": 0.417,
                "obp": 0.556,
                "slg": 0.583,
                "ops": 1.139,
                "tb": 14,
                "gdp": 0,
                "xbh": 4,
                "hbp": 1,
                "sac": 2,
                "roe": 0,
                "lob": 13,
                "barisp": 0.429,
                "babip": 0.455
            }
        },
        {
            "first": "Gene",
            "last": "Kassman",
            "number": 0,
            "stats": {
                "g": 9,
                "pa": 41,
                "ab": 29,
                "r": 11,
                "h": 8,
                "2b": 0,
                "3b": 0,
                "hr": 0,
                "rbi": 4,
                "sb": 4,
                "cs": 0,
                "bb": 9,
                "so": 5,
                "sol": 1,
                "ba": 0.276,
                "obp": 0.475,
                "slg": 0.276,
                "ops": 0.751,
                "tb": 8,
                "gdp": 1,
                "xbh": 0,
                "hbp": 2,
                "sac": 0,
                "roe": 1,
                "lob": 23,
                "barisp": 0.263,
                "babip": 0.333
            }
        },
        {
            "first": "Orin",
            "last": "Kierczynski",
            "number": 0,
            "stats": {
                "g": 8,
                "pa": 18,
                "ab": 12,
                "r": 5,
                "h": 4,
                "2b": 1,
                "3b": 0,
                "hr": 0,
                "rbi": 3,
                "sb": 0,
                "cs": 0,
                "bb": 6,
                "so": 6,
                "sol": 3,
                "ba": 0.333,
                "obp": 0.556,
                "slg": 0.417,
                "ops": 0.972,
                "tb": 5,
                "gdp": 0,
                "xbh": 1,
                "hbp": 0,
                "sac": 0,
                "roe": 0,
                "lob": 5,
                "barisp": 0.2,
                "babip": 0.667
            }
        },
        {
            "first": "Connor",
            "last": "LeGrange",
            "number": 0,
            "stats": {
                "g": 8,
                "pa": 15,
                "ab": 11,
                "r": 4,
                "h": 4,
                "2b": 1,
                "3b": 0,
                "hr": 0,
                "rbi": 3,
                "sb": 4,
                "cs": 0,
                "bb": 3,
                "so": 3,
                "sol": 0,
                "ba": 0.364,
                "obp": 0.533,
                "slg": 0.455,
                "ops": 0.988,
                "tb": 5,
                "gdp": 0,
                "xbh": 1,
                "hbp": 1,
                "sac": 0,
                "roe": 0,
                "lob": 10,
                "barisp": 0.286,
                "babip": 0.5
            }
        },
        {
            "first": "Hunter",
            "last": "Lord",
            "number": 0,
            "stats": {
                "g": 2,
                "pa": 9,
                "ab": 8,
                "r": 1,
                "h": 2,
                "2b": 0,
                "3b": 0,
                "hr": 0,
                "rbi": 3,
                "sb": 0,
                "cs": 0,
                "bb": 1,
                "so": 1,
                "sol": 1,
                "ba": 0.25,
                "obp": 0.333,
                "slg": 0.25,
                "ops": 0.583,
                "tb": 2,
                "gdp": 0,
                "xbh": 0,
                "hbp": 0,
                "sac": 0,
                "roe": 0,
                "lob": 6,
                "barisp": 0.4,
                "babip": 0.286
            }
        },
        {
            "first": "George",
            "last": "Omeir",
            "number": 0,
            "stats": {
                "g": 7,
                "pa": 34,
                "ab": 28,
                "r": 10,
                "h": 16,
                "2b": 5,
                "3b": 0,
                "hr": 1,
                "rbi": 13,
                "sb": 4,
                "cs": 0,
                "bb": 3,
                "so": 1,
                "sol": 1,
                "ba": 0.571,
                "obp": 0.588,
                "slg": 0.857,
                "ops": 1.445,
                "tb": 24,
                "gdp": 0,
                "xbh": 6,
                "hbp": 1,
                "sac": 2,
                "roe": 3,
                "lob": 10,
                "barisp": 0.571,
                "babip": 0.536
            }
        },
        {
            "first": "Austin",
            "last": "Orfield",
            "number": 0,
            "stats": {
                "g": 10,
                "pa": 48,
                "ab": 43,
                "r": 20,
                "h": 25,
                "2b": 5,
                "3b": 1,
                "hr": 0,
                "rbi": 11,
                "sb": 19,
                "cs": 0,
                "bb": 3,
                "so": 2,
                "sol": 0,
                "ba": 0.581,
                "obp": 0.604,
                "slg": 0.744,
                "ops": 1.348,
                "tb": 32,
                "gdp": 1,
                "xbh": 6,
                "hbp": 1,
                "sac": 1,
                "roe": 0,
                "lob": 14,
                "barisp": 0.5,
                "babip": 0.595
            }
        },
        {
            "first": "Nick",
            "last": "Restuccia",
            "number": 0,
            "stats": {
                "g": 4,
                "pa": 17,
                "ab": 15,
                "r": 2,
                "h": 4,
                "2b": 1,
                "3b": 0,
                "hr": 0,
                "rbi": 1,
                "sb": 0,
                "cs": 1,
                "bb": 1,
                "so": 4,
                "sol": 1,
                "ba": 0.267,
                "obp": 0.353,
                "slg": 0.333,
                "ops": 0.686,
                "tb": 5,
                "gdp": 0,
                "xbh": 1,
                "hbp": 1,
                "sac": 0,
                "roe": 1,
                "lob": 8,
                "barisp": 0.500,
                "babip": 0.308
            }
        },
        {
            "first": "Nathan",
            "last": "Rogers",
            "number": 0,
            "stats": {
                "g": 4,
                "pa": 15,
                "ab": 15,
                "r": 1,
                "h": 5,
                "2b": 2,
                "3b": 0,
                "hr": 1,
                "rbi": 6,
                "sb": 1,
                "cs": 0,
                "bb": 0,
                "so": 3,
                "sol": 0,
                "ba": 0.333,
                "obp": 0.333,
                "slg": 0.667,
                "ops": 1,
                "tb": 10,
                "gdp": 0,
                "xbh": 3,
                "hbp": 0,
                "sac": 0,
                "roe": 1,
                "lob": 8,
                "barisp": 0.333,
                "babip": 0.364
            }
        },
        {
            "first": "Chris",
            "last": "Vanderbosch",
            "number": 0,
            "stats": {
                "g": 2,
                "pa": 9,
                "ab": 7,
                "r": 1,
                "h": 1,
                "2b": 1,
                "3b": 0,
                "hr": 0,
                "rbi": 2,
                "sb": 2,
                "cs": 0,
                "bb": 2,
                "so": 2,
                "sol": 1,
                "ba": 0.143,
                "obp": 0.333,
                "slg": 0.286,
                "ops": 0.619,
                "tb": 2,
                "gdp": 0,
                "xbh": 1,
                "hbp": 0,
                "sac": 0,
                "roe": 0,
                "lob": 6,
                "barisp": 0.333,
                "babip": 0.2
            }
        },
        {
            "first": "Algenis",
            "last": "Vargas",
            "number": 0,
            "stats": {
                "g": 0,
                "pa": 0,
                "ab": 0,
                "r": 0,
                "h": 0,
                "2b": 0,
                "3b": 0,
                "hr": 0,
                "rbi": 0,
                "sb": 0,
                "cs": 0,
                "bb": 0,
                "so": 0,
                "sol": 0,
                "ba": 0,
                "obp": 0,
                "slg": 0,
                "ops": 0,
                "tb": 0,
                "gdp": 0,
                "xbh": 0,
                "hbp": 0,
                "sac": 0,
                "roe": 0,
                "lob": 0,
                "barisp": 0,
                "babip": 0
            }
        },
        {
            "first": "Mike",
            "last": "Wittner",
            "number": 0,
            "stats": {
                "g": 6,
                "pa": 22,
                "ab": 20,
                "r": 3,
                "h": 4,
                "2b": 2,
                "3b": 0,
                "hr": 0,
                "rbi": 0,
                "sb": 0,
                "cs": 0,
                "bb": 1,
                "so": 7,
                "sol": 2,
                "ba": 0.2,
                "obp": 0.273,
                "slg": 0.3,
                "ops": 0.573,
                "tb": 6,
                "gdp": 0,
                "xbh": 2,
                "hbp": 1,
                "sac": 0,
                "roe": 2,
                "lob": 10,
                "barisp": 0,
                "babip": 0.308
            }
        },
        {
            "first": "Zach",
            "last": "Wooley",
            "number": 0,
            "stats": {
                "g": 6,
                "pa": 26,
                "ab": 22,
                "r": 2,
                "h": 5,
                "2b": 1,
                "3b": 0,
                "hr": 0,
                "rbi": 7,
                "sb": 0,
                "cs": 0,
                "bb": 1,
                "so": 2,
                "sol": 2,
                "ba": 0.227,
                "obp": 0.308,
                "slg": 0.273,
                "ops": 0.58,
                "tb": 6,
                "gdp": 1,
                "xbh": 1,
                "hbp": 2,
                "sac": 1,
                "roe": 0,
                "lob": 15,
                "barisp": 0.25,
                "babip": 0.238
            }
        },
        {
            "first": "Aron",
            "last": "Zargapur",
            "number": 0,
            "stats": {
                "g": 10,
                "pa": 45,
                "ab": 42,
                "r": 10,
                "h": 13,
                "2b": 3,
                "3b": 0,
                "hr": 0,
                "rbi": 5,
                "sb": 1,
                "cs": 1,
                "bb": 2,
                "so": 12,
                "sol": 2,
                "ba": 0.31,
                "obp": 0.356,
                "slg": 0.381,
                "ops": 0.737,
                "tb": 16,
                "gdp": 2,
                "xbh": 3,
                "hbp": 1,
                "sac": 0,
                "roe": 3,
                "lob": 26,
                "barisp": 0.346,
                "babip": 0.433
            }
        },
        {
            "first": "Jake",
            "last": "Suppa",
            "number": 2,
            "stats": {
                "g": 4,
                "pa": 10,
                "ab": 8,
                "r": 2,
                "h": 1,
                "2b": 0,
                "3b": 0,
                "hr": 0,
                "rbi": 2,
                "sb": 0,
                "cs": 0,
                "bb": 1,
                "so": 2,
                "sol": 0,
                "ba": 0.125,
                "obp": 0.3,
                "slg": 0.125,
                "ops": 0.425,
                "tb": 1,
                "gdp": 0,
                "xbh": 0,
                "hbp": 1,
                "sac": 0,
                "roe": 0,
                "lob": 5,
                "barisp": 0.25,
                "babip": 0.167
            }
        },
        {
            "first": "Max",
            "last": "Schriner",
            "number": 27,
            "stats": {
                "g": 4,
                "pa": 11,
                "ab": 9,
                "r": 3,
                "h": 2,
                "2b": 1,
                "3b": 0,
                "hr": 0,
                "rbi": 3,
                "sb": 0,
                "cs": 0,
                "bb": 1,
                "so": 1,
                "sol": 0,
                "ba": 0.222,
                "obp": 0.364,
                "slg": 0.333,
                "ops": 0.697,
                "tb": 3,
                "gdp": 0,
                "xbh": 1,
                "hbp": 1,
                "sac": 0,
                "roe": 1,
                "lob": 8,
                "barisp": 0.167,
                "babip": 0.25
            }
        }
    ]
}